{
  "password": "admin123",
  "usdt": "jf",
  "tagline": "",
  "social": {
    "telegram": "",
    "whatsapp": "",
    "youtube": "",
    "facebook": ""
  },
  "products": [
    {
      "id": "1782238771840",
      "name": "gh",
      "price": 5,
      "category": "marketplace",
      "desc": "df",
      "pair": "df",
      "version": "MQL5",
      "type": "dr",
      "ytLink": "sdfg",
      "copy": "yes",
      "img": "",
      "resultImgs": [],
      "reviewImgs": []
    }
  ],
  "portfolio": []
}